src/adc.sv
// TSC simulation module

// set simulation time:
`timescale 1ns / 1ps

module ADC (
    input wire req,      // Request signal from TSC
    input wire rst,      // Reset signal for ADC
    output reg rdy,      // Ready signal to indicate completion
    output reg [7:0] dat // Data output from the array
);

// Constant array of values (16 data values)
  // reg [7:0]
  // integer adc_data [15:0] = {
  reg [0:7] adc_data [0:15];
    
  initial
    begin 
      // hard-coded ADC values stored in adc_data
      // it seams iVerilog doesn't want to initialize an array
      adc_data[ 0] = 8'h8B;
      adc_data[ 1] = 8'h8C;
      adc_data[ 2] = 8'h99;
      adc_data[ 3] = 8'h9B;
      adc_data[ 4] = 8'h93;
      adc_data[ 5] = 8'h82;
      adc_data[ 6] = 8'h97;
      adc_data[ 7] = 8'h90;
      adc_data[ 8] = 8'h9F;
      adc_data[ 9] = 8'hD7;
      adc_data[10] = 8'h8D;
      adc_data[11] = 8'h9C;
      adc_data[12] = 8'h85;
      adc_data[13] = 8'h8A;
      adc_data[14] = 8'h91;
      adc_data[15] = 8'h8C;
    end
  
  
  reg [7:0] idx = 0; // Index to access the array
  

always @(posedge req or posedge rst) begin
    if (rst) begin
        // Reset the device
        rdy <= 0;
        dat <= 8'b00000000; // Reset data output
        idx <= 0; // Reset array index
    end else if (req) begin
        // Read data from the sample array using modular arithmetic
        dat <= adc_data[idx % 16]; // Wrap around if idx exceeds 15
        idx <= idx + 1;

        // Raise RDY line
        rdy <= 1;
    end else begin
        // Lower RDY line if not processing
        rdy <= 0;
    end
end

endmodule

src/design.sv
`include "adc.sv"

`timescale 1ns / 1ps

module TSC (

    input wire reset,               // reset when high
    input wire start,               // start pulse
    input wire clk,                 // clock for TSC
    input wire [7:0] adc_data,      // data from adc
    input wire adc_rdy,             // ADC ready signal
    input wire sbf,                 // send buffer signal
    output reg req,                 // request line to ADC
    output reg trd,                 // trigger detected
    output reg cd,                  // completed data transfer
    output reg [31:0] trigtm,       // when trigger
    output reg sd                   // serial data out
);

    // State machine definitions
    localparam IDLE = 4'b0000;
    localparam RUNNING = 4'b0001;
    localparam TRIGGERED = 4'b0010;
    localparam BUFFER_SEND = 4'b0011;

    reg [3:0] state;
    reg [31:0] timer;
    reg [4:0] head;
    reg [4:0] tail;
    reg [7:0] ring_buffer [0:31];
    reg [7:0] trigvl = 8'd213;      // Trigger value (constant)
    reg [4:0] count;                // Counter for capturing additional values after trigger
    reg [4:0] byte_count;           // Counter for bytes transmitted
    reg [3:0] bit_count;            // Counter for bits transmitted within a byte
  
  	//reg 

    always @ (posedge clk) begin
        if (reset) begin
            state <= IDLE;
            timer <= 32'h0;
            head <= 5'b0;
            tail <= 5'b0;
            trd <= 1'b0;
            cd <= 1'b0;
            req <= 1'b0;
            count <= 5'b0;
            byte_count <= 5'b0;
            bit_count <= 4'b0;

        end else begin
            case (state)
                IDLE: begin
                    if (start) begin
                        state <= RUNNING;
                        req <= 1'b1;        // Start requesting data from ADC
                    end
                end
                RUNNING: begin
                  
                    if (adc_rdy) begin
                      	req <= 1'b0;
                      	
                        ring_buffer[tail] <= adc_data;      // Store data in ring buffer
                        
                        tail <= tail + 1;
                        if (adc_data >= trigvl) begin
                            state <= TRIGGERED;
                            trigtm <= timer;                // Store trigger time
                            count <= 5'b0;                  // Reset counter for capturing additional values
                        end 
                        req <= 1'b1;   
                    end
                    timer <= timer + 1;                     // Increment timer
                   
                end
                TRIGGERED: begin
                    req <= 1'b0;
                    if (adc_rdy) begin
                        ring_buffer[tail] <= adc_data;      // Store data in ring buffer
                        tail <= tail + 1;
                        count <= count + 1;
                        if (count == 5'd15) begin           // Captured 16 additional values
                            state <= IDLE;
                            trd <= 1'b1;                    // Set trigger detected flag
                            req <= 1'b0;                    // Stop requesting data from ADC
                        end
                        req <= 1'b1;
                    end
                end
                BUFFER_SEND: begin
                  if (byte_count < 32) begin
                      if (bit_count == 4'b0) begin
                            sd <= 1'b1;                     // Set SD high at the start of each byte
                            cd <= 1'b0;                     // Set CD low
                            bit_count = bit_count + 4'b1;
                      end else if (bit_count == 4'b1) begin
                            //sd <= 1'b0;                     // Set SD low for start bit
                            bit_count = bit_count + 4'b1;
                          //cd <= 1'b1; test
                      end else if (bit_count < 4'b1010) begin
                        
                        sd <= ring_buffer[(tail - byte_count - 1'b1) % 32][bit_count - 4'b0010]; // Send data bits
                            bit_count = bit_count + 4'b1;
                          //cd <= 1'b1; //test
                          //sd <=0;//test
                        end else begin
                            byte_count = byte_count + 5'b1;
                            bit_count = 4'b0;
                          	cd <=1'b1; //test if code reaches this part
                        end
                    end else begin
                        state <= IDLE;
                        cd <= 1'b1;                         // Set CD high to indicate transfer completion
                        byte_count = 5'b0;
                        bit_count = 4'b0;
                    end

                end
              default :
                state = IDLE;
            endcase
            
            if (sbf) begin
                state <= BUFFER_SEND;                       // Enter buffer sending mode
                byte_count <= 5'b0;                         // Reset byte counter
                bit_count <= 3'b000;                        // Reset bit counter
            end
        end
    end

endmodule

src/testbench.sv
// Code your testbench here
// or browse Examples
// Test bench simulator for TSC
`timescale 1ns / 1ps

module TSC_tb;
  	// Parameters
    parameter CLK_PERIOD = 10; // Clock period in ns

    // Signals
    reg reset;
    reg start;
    reg clk;
    reg [7:0] adc_data;
    reg adc_rdy;
    reg sbf;
    wire req;
    wire trd;
    wire cd;
    wire [31:0] trigtm;
    wire sd;

    // Instantiate TSC module
    TSC tsc_inst (
        .reset(reset),
        .start(start),
        .clk(clk),
        .adc_data(adc_data),
        .adc_rdy(adc_rdy),
        .sbf(sbf),
        .req(req),
        .trd(trd),
        .cd(cd),
        .trigtm(trigtm),
        .sd(sd)
    );
  
    // Instantiate ADC module
    ADC adc_inst (
      .req(req),
      .rst(reset),
      .rdy(adc_rdy),
      .dat(adc_data)
    );
  
  

    // Clock generation
    always #(CLK_PERIOD / 2) clk = ~clk;

    // Testbench logic
    initial begin
    	$dumpfile("dump.vcd");
       	$dumpvars;
        // Initialize signals
        reset = 1;
        start = 0;
        clk = 0;
        //adc_data = 0;
        //adc_rdy = 0;
        sbf = 0;

        // Reset TSC
        #10;
        reset = 0;
        $display("TSC reset");

        // Start TSC
        #10;
        start = 1;
        #10;
        start = 0;
        $display("TSC started");

        // Simulate ADC data and ready signal
        $monitor("time:%t, data: %h",$realtime, adc_data);
        repeat (50) begin
            #10;
            //adc_data = $random;
          	start = 1;
            //adc_rdy = 1;
          
            #10;
            //adc_rdy = 0;
            start = 0;
        end

        // Trigger buffer sending
      $monitor("cd: %d sd: %d", cd,sd); 
        #10;
        sbf = 1;
      	
        #10;
        sbf = 0;
        $display("Buffer sending triggered");

        // Wait for transmission to complete
        wait(cd);
        $display("Transmission completed");

        // End simulation
        //#40;
        $finish;
    end
endmodule

dump.vcd
$date
	Mon Apr 29 15:16:10 2024
$end
$version
	Icarus Verilog
$end
$timescale
	1ps
$end
$scope module TSC_tb $end
$var wire 32 ! trigtm [31:0] $end
$var wire 1 " trd $end
$var wire 1 # sd $end
$var wire 1 $ req $end
$var wire 1 % cd $end
$var wire 1 & adc_rdy $end
$var wire 8 ' adc_data [7:0] $end
$var reg 1 ( clk $end
$var reg 1 ) reset $end
$var reg 1 * sbf $end
$var reg 1 + start $end
$scope module adc_inst $end
$var wire 1 ) rst $end
$var wire 1 $ req $end
$var reg 8 , dat [7:0] $end
$var reg 8 - idx [7:0] $end
$var reg 1 & rdy $end
$upscope $end
$scope module tsc_inst $end
$var wire 8 . adc_data [7:0] $end
$var wire 1 & adc_rdy $end
$var wire 1 ( clk $end
$var wire 1 ) reset $end
$var wire 1 * sbf $end
$var wire 1 + start $end
$var reg 4 / bit_count [3:0] $end
$var reg 5 0 byte_count [4:0] $end
$var reg 1 % cd $end
$var reg 5 1 count [4:0] $end
$var reg 5 2 head [4:0] $end
$var reg 1 $ req $end
$var reg 1 # sd $end
$var reg 4 3 state [3:0] $end
$var reg 5 4 tail [4:0] $end
$var reg 32 5 timer [31:0] $end
$var reg 1 " trd $end
$var reg 32 6 trigtm [31:0] $end
$var reg 8 7 trigvl [7:0] $end
$upscope $end
$upscope $end
$enddefinitions $end
#0
$dumpvars
b11010101 7
bx 6
bx 5
bx 4
bx 3
bx 2
bx 1
bx 0
bx /
b0 .
b0 -
b0 ,
0+
0*
1)
0(
b0 '
0&
x%
x$
x#
x"
bx !
$end
#5000
b0 /
b0 0
b0 1
0$
0%
0"
b0 4
b0 2
b0 5
b0 3
1(
#10000
0(
0)
#15000
1(
#20000
0(
1+
#25000
1&
b1 -
b10001011 '
b10001011 ,
b10001011 .
1$
b1 3
1(
#30000
0(
0+
#35000
b10 -
b10001100 '
b10001100 ,
b10001100 .
b1 5
b1 4
1$
1(
#40000
0(
1+
#45000
b11 -
b10011001 '
b10011001 ,
b10011001 .
b10 5
b10 4
1$
1(
#50000
0(
0+
#55000
b100 -
b10011011 '
b10011011 ,
b10011011 .
b11 5
b11 4
1$
1(
#60000
0(
1+
#65000
b101 -
b10010011 '
b10010011 ,
b10010011 .
b100 5
b100 4
1$
1(
#70000
0(
0+
#75000
b110 -
b10000010 '
b10000010 ,
b10000010 .
b101 5
b101 4
1$
1(
#80000
0(
1+
#85000
b111 -
b10010111 '
b10010111 ,
b10010111 .
b110 5
b110 4
1$
1(
#90000
0(
0+
#95000
b1000 -
b10010000 '
b10010000 ,
b10010000 .
b111 5
b111 4
1$
1(
#100000
0(
1+
#105000
b1001 -
b10011111 '
b10011111 ,
b10011111 .
b1000 5
b1000 4
1$
1(
#110000
0(
0+
#115000
b1010 -
b11010111 '
b11010111 ,
b11010111 .
b1001 5
b1001 4
1$
1(
#120000
0(
1+
#125000
b1011 -
b10001101 '
b10001101 ,
b10001101 .
b1010 5
b1001 !
b1001 6
b10 3
b1010 4
1$
1(
#130000
0(
0+
#135000
b1100 -
b10011100 '
b10011100 ,
b10011100 .
b1 1
b1011 4
1$
1(
#140000
0(
1+
#145000
b1101 -
b10000101 '
b10000101 ,
b10000101 .
b10 1
b1100 4
1$
1(
#150000
0(
0+
#155000
b1110 -
b10001010 '
b10001010 ,
b10001010 .
b11 1
b1101 4
1$
1(
#160000
0(
1+
#165000
b1111 -
b10010001 '
b10010001 ,
b10010001 .
b100 1
b1110 4
1$
1(
#170000
0(
0+
#175000
b10000 -
b10001100 '
b10001100 ,
b10001100 .
b101 1
b1111 4
1$
1(
#180000
0(
1+
#185000
b10001 -
b10001011 '
b10001011 ,
b10001011 .
b110 1
b10000 4
1$
1(
#190000
0(
0+
#195000
b10010 -
b10001100 '
b10001100 ,
b10001100 .
b111 1
b10001 4
1$
1(
#200000
0(
1+
#205000
b10011 -
b10011001 '
b10011001 ,
b10011001 .
b1000 1
b10010 4
1$
1(
#210000
0(
0+
#215000
b10100 -
b10011011 '
b10011011 ,
b10011011 .
b1001 1
b10011 4
1$
1(
#220000
0(
1+
#225000
b10101 -
b10010011 '
b10010011 ,
b10010011 .
b1010 1
b10100 4
1$
1(
#230000
0(
0+
#235000
b10110 -
b10000010 '
b10000010 ,
b10000010 .
b1011 1
b10101 4
1$
1(
#240000
0(
1+
#245000
b10111 -
b10010111 '
b10010111 ,
b10010111 .
b1100 1
b10110 4
1$
1(
#250000
0(
0+
#255000
b11000 -
b10010000 '
b10010000 ,
b10010000 .
b1101 1
b10111 4
1$
1(
#260000
0(
1+
#265000
b11001 -
b10011111 '
b10011111 ,
b10011111 .
b1110 1
b11000 4
1$
1(
#270000
0(
0+
#275000
b11010 -
b11010111 '
b11010111 ,
b11010111 .
b1111 1
b11001 4
1$
1(
#280000
0(
1+
#285000
b11011 -
b10001101 '
b10001101 ,
b10001101 .
1"
b0 3
b10000 1
b11010 4
1$
1(
#290000
0(
0+
#295000
1(
#300000
0(
1+
#305000
b1 3
1(
#310000
0(
0+
#315000
b11100 -
b10011100 '
b10011100 ,
b10011100 .
b1011 5
b11011 4
1$
1(
#320000
0(
1+
#325000
b11101 -
b10000101 '
b10000101 ,
b10000101 .
b1100 5
b11100 4
1$
1(
#330000
0(
0+
#335000
b11110 -
b10001010 '
b10001010 ,
b10001010 .
b1101 5
b11101 4
1$
1(
#340000
0(
1+
#345000
b11111 -
b10010001 '
b10010001 ,
b10010001 .
b1110 5
b11110 4
1$
1(
#350000
0(
0+
#355000
b100000 -
b10001100 '
b10001100 ,
b10001100 .
b1111 5
b11111 4
1$
1(
#360000
0(
1+
#365000
b100001 -
b10001011 '
b10001011 ,
b10001011 .
b10000 5
b0 4
1$
1(
#370000
0(
0+
#375000
b100010 -
b10001100 '
b10001100 ,
b10001100 .
b10001 5
b1 4
1$
1(
#380000
0(
1+
#385000
b100011 -
b10011001 '
b10011001 ,
b10011001 .
b10010 5
b10 4
1$
1(
#390000
0(
0+
#395000
b100100 -
b10011011 '
b10011011 ,
b10011011 .
b10011 5
b11 4
1$
1(
#400000
0(
1+
#405000
b100101 -
b10010011 '
b10010011 ,
b10010011 .
b10100 5
b100 4
1$
1(
#410000
0(
0+
#415000
b100110 -
b10000010 '
b10000010 ,
b10000010 .
b10101 5
b101 4
1$
1(
#420000
0(
1+
#425000
b100111 -
b10010111 '
b10010111 ,
b10010111 .
b10110 5
b110 4
1$
1(
#430000
0(
0+
#435000
b101000 -
b10010000 '
b10010000 ,
b10010000 .
b10111 5
b111 4
1$
1(
#440000
0(
1+
#445000
b101001 -
b10011111 '
b10011111 ,
b10011111 .
b11000 5
b1000 4
1$
1(
#450000
0(
0+
#455000
b101010 -
b11010111 '
b11010111 ,
b11010111 .
b11001 5
b1001 4
1$
1(
#460000
0(
1+
#465000
b101011 -
b10001101 '
b10001101 ,
b10001101 .
b11010 5
b0 1
b11001 !
b11001 6
b10 3
b1010 4
1$
1(
#470000
0(
0+
#475000
b101100 -
b10011100 '
b10011100 ,
b10011100 .
b1 1
b1011 4
1$
1(
#480000
0(
1+
#485000
b101101 -
b10000101 '
b10000101 ,
b10000101 .
b10 1
b1100 4
1$
1(
#490000
0(
0+
#495000
b101110 -
b10001010 '
b10001010 ,
b10001010 .
b11 1
b1101 4
1$
1(
#500000
0(
1+
#505000
b101111 -
b10010001 '
b10010001 ,
b10010001 .
b100 1
b1110 4
1$
1(
#510000
0(
0+
#515000
b110000 -
b10001100 '
b10001100 ,
b10001100 .
b101 1
b1111 4
1$
1(
#520000
0(
1+
#525000
b110001 -
b10001011 '
b10001011 ,
b10001011 .
b110 1
b10000 4
1$
1(
#530000
0(
0+
#535000
b110010 -
b10001100 '
b10001100 ,
b10001100 .
b111 1
b10001 4
1$
1(
#540000
0(
1+
#545000
b110011 -
b10011001 '
b10011001 ,
b10011001 .
b1000 1
b10010 4
1$
1(
#550000
0(
0+
#555000
b110100 -
b10011011 '
b10011011 ,
b10011011 .
b1001 1
b10011 4
1$
1(
#560000
0(
1+
#565000
b110101 -
b10010011 '
b10010011 ,
b10010011 .
b1010 1
b10100 4
1$
1(
#570000
0(
0+
#575000
b110110 -
b10000010 '
b10000010 ,
b10000010 .
b1011 1
b10101 4
1$
1(
#580000
0(
1+
#585000
b110111 -
b10010111 '
b10010111 ,
b10010111 .
b1100 1
b10110 4
1$
1(
#590000
0(
0+
#595000
b111000 -
b10010000 '
b10010000 ,
b10010000 .
b1101 1
b10111 4
1$
1(
#600000
0(
1+
#605000
b111001 -
b10011111 '
b10011111 ,
b10011111 .
b1110 1
b11000 4
1$
1(
#610000
0(
0+
#615000
b111010 -
b11010111 '
b11010111 ,
b11010111 .
b1111 1
b11001 4
1$
1(
#620000
0(
1+
#625000
b111011 -
b10001101 '
b10001101 ,
b10001101 .
b0 3
b10000 1
b11010 4
1$
1(
#630000
0(
0+
#635000
1(
#640000
0(
1+
#645000
b1 3
1(
#650000
0(
0+
#655000
b111100 -
b10011100 '
b10011100 ,
b10011100 .
b11011 5
b11011 4
1$
1(
#660000
0(
1+
#665000
b111101 -
b10000101 '
b10000101 ,
b10000101 .
b11100 5
b11100 4
1$
1(
#670000
0(
0+
#675000
b111110 -
b10001010 '
b10001010 ,
b10001010 .
b11101 5
b11101 4
1$
1(
#680000
0(
1+
#685000
b111111 -
b10010001 '
b10010001 ,
b10010001 .
b11110 5
b11110 4
1$
1(
#690000
0(
0+
#695000
b1000000 -
b10001100 '
b10001100 ,
b10001100 .
b11111 5
b11111 4
1$
1(
#700000
0(
1+
#705000
b1000001 -
b10001011 '
b10001011 ,
b10001011 .
b100000 5
b0 4
1$
1(
#710000
0(
0+
#715000
b1000010 -
b10001100 '
b10001100 ,
b10001100 .
b100001 5
b1 4
1$
1(
#720000
0(
1+
#725000
b1000011 -
b10011001 '
b10011001 ,
b10011001 .
b100010 5
b10 4
1$
1(
#730000
0(
0+
#735000
b1000100 -
b10011011 '
b10011011 ,
b10011011 .
b100011 5
b11 4
1$
1(
#740000
0(
1+
#745000
b1000101 -
b10010011 '
b10010011 ,
b10010011 .
b100100 5
b100 4
1$
1(
#750000
0(
0+
#755000
b1000110 -
b10000010 '
b10000010 ,
b10000010 .
b100101 5
b101 4
1$
1(
#760000
0(
1+
#765000
b1000111 -
b10010111 '
b10010111 ,
b10010111 .
b100110 5
b110 4
1$
1(
#770000
0(
0+
#775000
b1001000 -
b10010000 '
b10010000 ,
b10010000 .
b100111 5
b111 4
1$
1(
#780000
0(
1+
#785000
b1001001 -
b10011111 '
b10011111 ,
b10011111 .
b101000 5
b1000 4
1$
1(
#790000
0(
0+
#795000
b1001010 -
b11010111 '
b11010111 ,
b11010111 .
b101001 5
b1001 4
1$
1(
#800000
0(
1+
#805000
b1001011 -
b10001101 '
b10001101 ,
b10001101 .
b101010 5
b0 1
b101001 !
b101001 6
b10 3
b1010 4
1$
1(
#810000
0(
0+
#815000
b1001100 -
b10011100 '
b10011100 ,
b10011100 .
b1 1
b1011 4
1$
1(
#820000
0(
1+
#825000
b1001101 -
b10000101 '
b10000101 ,
b10000101 .
b10 1
b1100 4
1$
1(
#830000
0(
0+
#835000
b1001110 -
b10001010 '
b10001010 ,
b10001010 .
b11 1
b1101 4
1$
1(
#840000
0(
1+
#845000
b1001111 -
b10010001 '
b10010001 ,
b10010001 .
b100 1
b1110 4
1$
1(
#850000
0(
0+
#855000
b1010000 -
b10001100 '
b10001100 ,
b10001100 .
b101 1
b1111 4
1$
1(
#860000
0(
1+
#865000
b1010001 -
b10001011 '
b10001011 ,
b10001011 .
b110 1
b10000 4
1$
1(
#870000
0(
0+
#875000
b1010010 -
b10001100 '
b10001100 ,
b10001100 .
b111 1
b10001 4
1$
1(
#880000
0(
1+
#885000
b1010011 -
b10011001 '
b10011001 ,
b10011001 .
b1000 1
b10010 4
1$
1(
#890000
0(
0+
#895000
b1010100 -
b10011011 '
b10011011 ,
b10011011 .
b1001 1
b10011 4
1$
1(
#900000
0(
1+
#905000
b1010101 -
b10010011 '
b10010011 ,
b10010011 .
b1010 1
b10100 4
1$
1(
#910000
0(
0+
#915000
b1010110 -
b10000010 '
b10000010 ,
b10000010 .
b1011 1
b10101 4
1$
1(
#920000
0(
1+
#925000
b1010111 -
b10010111 '
b10010111 ,
b10010111 .
b1100 1
b10110 4
1$
1(
#930000
0(
0+
#935000
b1011000 -
b10010000 '
b10010000 ,
b10010000 .
b1101 1
b10111 4
1$
1(
#940000
0(
1+
#945000
b1011001 -
b10011111 '
b10011111 ,
b10011111 .
b1110 1
b11000 4
1$
1(
#950000
0(
0+
#955000
b1011010 -
b11010111 '
b11010111 ,
b11010111 .
b1111 1
b11001 4
1$
1(
#960000
0(
1+
#965000
b1011011 -
b10001101 '
b10001101 ,
b10001101 .
b0 3
b10000 1
b11010 4
1$
1(
#970000
0(
0+
#975000
1(
#980000
0(
1+
#985000
b1 3
1(
#990000
0(
0+
#995000
b1011100 -
b10011100 '
b10011100 ,
b10011100 .
b101011 5
b11011 4
1$
1(
#1000000
0(
1+
#1005000
b1011101 -
b10000101 '
b10000101 ,
b10000101 .
b101100 5
b11100 4
1$
1(
#1010000
0(
0+
#1015000
b1011110 -
b10001010 '
b10001010 ,
b10001010 .
b101101 5
b11101 4
1$
1(
#1020000
0(
1+
#1025000
b1011111 -
b10010001 '
b10010001 ,
b10010001 .
b101110 5
b11110 4
1$
1(
#1030000
0(
0+
#1035000
b1100000 -
b10001100 '
b10001100 ,
b10001100 .
b101111 5
b11111 4
1$
1(
#1040000
0(
1*
#1045000
b1100001 -
b10001011 '
b10001011 ,
b10001011 .
b11 3
b110000 5
b0 4
1$
1(
#1050000
0(
0*
#1055000
1#
b1 /
1(
#1060000
0(
#1065000
b10 /
1(
#1070000
0(
#1075000
0#
b11 /
1(
#1080000
0(
#1085000
b100 /
1(
#1090000
0(
#1095000
1#
b101 /
1(
#1100000
0(
#1105000
b110 /
1(
#1110000
0(
#1115000
0#
b111 /
1(
#1120000
0(
#1125000
b1000 /
1(
#1130000
0(
#1135000
b1001 /
1(
#1140000
0(
#1145000
1#
b1010 /
1(
#1150000
0(
#1155000
1%
b0 /
b1 0
1(
