src/adc.v
// TSC simulation module

// set simulation time:
`timescale 1ns / 1ps

module ADC (
    input wire req,      // Request signal from TSC
    input wire rst,      // Reset signal for ADC
    output reg rdy,      // Ready signal to indicate completion
    output reg [11:0] dat // Data output from the array
);

// Constant array of values (16 data values)
reg [0:11] adc_data [0:15];
integer idx = 0;

initial begin
        $readmemh("adc_data.txt", adc_data);
    end 

always @(posedge req or posedge rst) begin
    if (rst) begin
        // Reset the device
        rdy <= 0;
        dat <= 8'b00000000; // Reset data output
        idx <= 0; // Reset array index
    end else if (req) begin
        // Read data from the sample array using modular arithmetic
        dat <= adc_data[idx]; 
        // Increment idx on the falling edge of req
        idx <= (idx + 1) % 16; // Increment index and Wrap around if idx exceeds 15
        // Raise RDY line
        rdy <= 1;
    end else begin
        // Lower RDY line if not processing
        rdy <= 0;
    end
end

endmodule





  // initial
  //   begin 
  //     // hard-coded ADC values stored in adc_data
  //     // it seams iVerilog doesn't want to initialize an array
  //     adc_data[ 0] = 8'h8B;
  //     adc_data[ 1] = 8'h8C;
  //     adc_data[ 2] = 8'h99;
  //     adc_data[ 3] = 8'h9B;
  //     adc_data[ 4] = 8'h93;
  //     adc_data[ 5] = 8'h82;
  //     adc_data[ 6] = 8'h97;
  //     adc_data[ 7] = 8'h90;
  //     adc_data[ 8] = 8'h9F;
  //     adc_data[ 9] = 8'hD7;
  //     adc_data[10] = 8'h8D;
  //     adc_data[11] = 8'h9C;
  //     adc_data[12] = 8'h85;
  //     adc_data[13] = 8'h8A;
  //     adc_data[14] = 8'h91;
  //     adc_data[15] = 8'h8C;
  //   end
  
  
//reg [7:0] idx = 0; // Index to access the array

src/tsc.v
`timescale 1ns / 1ps

module TSC (

    input wire reset,               // reset when high
    input wire start,               // start pulse
    input wire clk,                 // clock for TSC
    input wire [7:0] adc_data,      // data from adc
    input wire adc_rdy,             // ADC ready signal connected to the ADC
    input wire sbf,                 // send buffer signal from the test bench

    output reg req,                 // request line to ADC
    output reg trd,                 // trigger detected
    output reg cd,                  // completed data transfer
    output reg [31:0] trigtm,       // Timer when TSC module is triggered
    output reg sd                   // serial data out
);



    // state machine definitions for the TSC module 

    localparam IDLE = 0;
    localparam RUNNING = 1;
    localparam TRIGGERED = 2;
    localparam BUFFER_SEND = 3;
    localparam START_BIT = 4;
    localparam DATA_BIT = 5;
    localparam COMPLETE = 6;

    // regs for the state machine
    reg [3:0] state = IDLE;
    reg [31:0] timer = 0;
    reg [4:0] head = 0;                     //stores the index of the head of the ring buffer
    reg [4:0] tail = 0;                     // stores the index of the tail of the ring buffer 
    reg [7:0] ring_buffer [31:0];           // 32 byte ring buffer to store adc values
    reg [7:0] trigvl = 8'd208;              // Trigger value (constant)
    reg [4:0] post_count = 0;                // Counter for capturing additional values after trigger
    reg [4:0] byte_count = 31;           // Counter for bytes transmitted
    reg [3:0] bit_count = 8;            // Counter for bits transmitted within a byte

    
    initial begin
        integer i;
        for (i = 0; i < 32; ++i) begin
            ring_buffer[i] = 8'h0;          // initializing the values in the ring buffer to 0
        end
    end

    always @ (posedge clk) begin                // synchronizing on the rising edge of the clock
        if (reset) begin
            $display("RESET");
            state <= IDLE;
            timer <= 32'h0;
            head <= 5'b0;
            tail <= 5'b0;
            trd <= 1'b0;
            cd <= 1'b0;                         // initial values 
            req <= 1'b0;
            post_count <= 5'b0;
            byte_count <= 31;
            bit_count <= 8;
            trigtm <= 32'h0;

        end else begin
            case (state)
                IDLE: begin
                    if (start) begin
                        trd <= 0;
                        cd <= 0;
                        req <= 1'b1;        // Start requesting data from ADC
                        state <= RUNNING;
                    end else if (sbf) begin
                        state <= BUFFER_SEND;  // Transition to BUFFER_SEND state when sbf is asserted by the test bench
                    end
                end
                RUNNING: begin
                    timer++;                       // Increment timer
                    $display("RUNNING");
                    if (adc_rdy) begin
                        ring_buffer[tail] <= adc_data;      // Store data in ring buffer
                        tail <= (tail + 1) % 32; 
                        $display("Data received: %h -> %b", adc_data, adc_data);  // showing the data received from the adc
                        if (adc_data > trigvl) begin
                            trigtm <= timer;                    // Store trigger time
                            post_count <= 16;                  // Reset counter for capturing additional values after the trigger event
                            state <= TRIGGERED;
                        end
                        req <= 0;  // Set req to 0 after receiving data
                    
                        req <= 1;  // Set req to 1 to request next data
                    end
                end
                TRIGGERED: begin
                    timer++; 
                    $display("TRIGGERED");
                    if (post_count > 0) begin
                        ring_buffer[tail] <= adc_data;      // Store data in ring buffer
                        tail <= (tail + 1) % 32;            // Wrap around tail pointer
                        post_count <= post_count -1;
                        $display("Data received: %h -> %b", adc_data, adc_data);
                        
                        req <= 0;  // Set req to 0 after receiving data
                        
                        req <= 1;  // Set req to 1 to request next data

                    end else begin 
                        $display("TRANSITION TO BUFFER_SEND");
                        trd <= 1;  // set trigger detect high
                        state <= IDLE;
                    end
                end
                BUFFER_SEND: begin
                    $display("BUFFER_SEND");
                    sd <= 1;
                    cd <= 0;
                    state <= START_BIT;
                end
                START_BIT: begin
                    @ (negedge clk)begin
                        $display("Sending start bit");
                        sd <= 0;  // Set SD line to low for start bit
                        bit_count <= 7;
                        state <= DATA_BIT;
                    end
                end

                DATA_BIT: begin
                    @ (negedge clk)begin
                        $display("Sending bit %d for data %b (%h)", bit_count, ring_buffer[head], ring_buffer[head]);
                        //$display("Sending data bit %d for data %b (%h)", bit_count, ring_buffer[(tail - byte_count - 1) % 32], ring_buffer[(tail - byte_count - 1) % 32]);
                        //sd <= ring_buffer[(tail - byte_count - 1) % 32][bit_count];  
                        sd <= ring_buffer[head][bit_count];  // Transmit data bit big endian (MSB first)
                        if (bit_count > 0) begin                
                            bit_count <= bit_count - 1;
                        end else begin

                            if (byte_count == 0) begin
                                state <= COMPLETE;
                                
                            end else begin
                                byte_count <= byte_count - 1;
                                head <= (head + 1) % 32;
                                bit_count <= 8;
                                state <= START_BIT;  // Transition to START_BIT state for the next byte
                            end
                        end
                    end
                end
                COMPLETE: begin
                    @(posedge clk);  // Wait for one more clock pulse
                    cd <= 1;  // Set CD line to high to indicate transfer completion
                    sd <= 0;
                    state <= IDLE;
                end
            endcase
        end
    end
endmodule

src/tsc_tb.v

`timescale 1ns / 1ps

module tsc_tb;

    // TSC inputs
    reg reset;
    reg start;
    reg clk;
    reg sbf;
    
    // ADC outputs
    wire [7:0] adc_data;
    wire adc_rdy;
    
    // TSC outputs
    wire req;
    wire trd;
    wire cd;
    wire [31:0] trigtm;
    wire sd;

    // Instantiate the TSC module
    TSC tsc_inst (
        .reset(reset),
        .start(start),
        .clk(clk),
        .adc_data(adc_data),
        .adc_rdy(adc_rdy),
        .sbf(sbf),
        .req(req),
        .trd(trd),
        .cd(cd),
        .trigtm(trigtm),
        .sd(sd)
    );

    // Instantiate the ADC module
    ADC adc_inst (
        .req(req),
        .rst(reset),
        .rdy(adc_rdy),
        .dat(adc_data)
    );

    // Clock generation
    always #5 clk = ~clk; // every 5 clock units

   
    integer i;      // serial data printing and verification 
    integer j;

    integer sd_indx = 0;
    reg prev_indx = 0;
    reg [255:0] sd_values;          // Serial data reading and capturing for verification
    reg [7:0] byte_val;
    reg [7:0] bit_count = 0;
    

    localparam WAIT_BF_SEND = 2'b00,
               STORE_SD = 2'b01,
               WAIT_START_BIT = 2'b10;

    reg [1:0] sd_state = WAIT_BF_SEND;


    always @(posedge clk) begin
        case (sd_state)
            WAIT_BF_SEND: begin
                if (sd && !prev_indx) begin
                    // Clear the SD values
                    for (i = 0; i < 256; i = i + 1) begin
                        sd_values[i] = 0;
                    end
                    sd_state <= WAIT_START_BIT;
                end
            end
            WAIT_START_BIT: begin
                // SD pulled low in start bit state
                if (!sd) begin
                    sd_state <= STORE_SD;
                end
            end
            STORE_SD: begin
                sd_values[sd_indx] = sd;
                sd_indx ++;
                bit_count ++;
                if (bit_count == 8) begin
                    bit_count = 0;
                    sd_state <= WAIT_START_BIT;
                end
            end
        endcase
    end

    initial begin               // initial begin and initializing inputs
        reset = 1;
        start = 0;
        clk = 0;
        sbf = 0;

        
        #100;
        reset = 0;              // Release reset after some delay

        // Start the TSC
        #20;
        start = 1;              // wait small delay
        #10;
        start = 0;

        // Wait for trigger detection
        wait(trd);
        $display("Trigger detected at time %d", $time);

        // assert the send buffer signal
        sbf = 1;

        // Wait for data transfer completion
        wait(cd);
        // assert send buffer low
        sbf = 0;
        $display("Data transfer completed at time %d", $time);
        
        // Wait for a few clock cycles to observe the data transmission
        #1000


        // Print the received bytes from the TSC module
        for (i = 0; i < 256; i = i + 8) begin
            byte_val = 0;
            for (j = 0; j < 8; j = j + 1) begin
                byte_val = byte_val << 1;
                byte_val[0] = sd_values[i + j];
            end
            $display("Serial data value at index %d: %d -> in hex = %h -> in binary = %b", i, byte_val, byte_val, byte_val);
        end

        // Wait for some time
        #100;

        // End the simulation
        $finish;
    end

    initial begin
        $dumpfile("dump.vcd");
        $dumpvars; 
    end
endmodule

dump.vcd
$date
	Wed May  1 17:49:10 2024
$end
$version
	Icarus Verilog
$end
$timescale
	1ps
$end
$scope module tsc_tb $end
$var wire 32 ! trigtm [31:0] $end
$var wire 1 " trd $end
$var wire 1 # sd $end
$var wire 1 $ req $end
$var wire 1 % cd $end
$var wire 1 & adc_rdy $end
$var wire 8 ' adc_data [7:0] $end
$var reg 8 ( bit_count [7:0] $end
$var reg 8 ) byte_val [7:0] $end
$var reg 1 * clk $end
$var reg 1 + prev_indx $end
$var reg 1 , reset $end
$var reg 1 - sbf $end
$var reg 2 . sd_state [1:0] $end
$var reg 256 / sd_values [255:0] $end
$var reg 1 0 start $end
$var integer 32 1 i [31:0] $end
$var integer 32 2 j [31:0] $end
$var integer 32 3 sd_indx [31:0] $end
$scope module adc_inst $end
$var wire 1 , rst $end
$var wire 1 $ req $end
$var reg 12 4 dat [11:0] $end
$var reg 1 & rdy $end
$var integer 32 5 idx [31:0] $end
$upscope $end
$scope module tsc_inst $end
$var wire 8 6 adc_data [7:0] $end
$var wire 1 & adc_rdy $end
$var wire 1 * clk $end
$var wire 1 , reset $end
$var wire 1 - sbf $end
$var wire 1 0 start $end
$var reg 4 7 bit_count [3:0] $end
$var reg 5 8 byte_count [4:0] $end
$var reg 1 % cd $end
$var reg 5 9 head [4:0] $end
$var reg 5 : post_count [4:0] $end
$var reg 1 $ req $end
$var reg 1 # sd $end
$var reg 4 ; state [3:0] $end
$var reg 5 < tail [4:0] $end
$var reg 32 = timer [31:0] $end
$var reg 1 " trd $end
$var reg 32 > trigtm [31:0] $end
$var reg 8 ? trigvl [7:0] $end
$scope begin $unm_blk_1 $end
$var integer 32 @ i [31:0] $end
$upscope $end
$upscope $end
$upscope $end
$enddefinitions $end
#0
$dumpvars
b100000 @
b11010000 ?
bx >
b0 =
b0 <
b0 ;
b0 :
b0 9
b11111 8
b1000 7
b0 6
b0 5
b0 4
b0 3
bx 2
bx 1
00
bx /
b0 .
0-
1,
0+
0*
bx )
b0 (
b0 '
0&
x%
x$
x#
x"
bx !
$end
#5000
b0 !
b0 >
0$
0%
0"
1*
#10000
0*
#15000
1*
#20000
0*
#25000
1*
#30000
0*
#35000
1*
#40000
0*
#45000
1*
#50000
0*
#55000
1*
#60000
0*
#65000
1*
#70000
0*
#75000
1*
#80000
0*
#85000
1*
#90000
0*
#95000
1*
#100000
0*
0,
#105000
1*
#110000
0*
#115000
1*
#120000
0*
10
#125000
b1000000 '
b1000000 6
1&
b1 5
b1000000 4
b1 ;
1$
1*
#130000
0*
00
#135000
b10100100 '
b10100100 6
b10 5
b10100100 4
1$
b1 <
b1 =
1*
#140000
0*
#145000
b10110000 '
b10110000 6
b11 5
b10110000 4
1$
b10 <
b10 =
1*
#150000
0*
#155000
b11010000 '
b11010000 6
b100 5
b11010000 4
1$
b11 <
b11 =
1*
#160000
0*
#165000
b11111111 '
b11111111 6
b101 5
b11111111 4
1$
b100 <
b100 =
1*
#170000
0*
#175000
b0 '
b0 6
b110 5
b100000000 4
1$
b10 ;
b10000 :
b101 !
b101 >
b101 <
b101 =
1*
#180000
0*
#185000
b1011110 '
b1011110 6
b111 5
b101011110 4
1$
b1111 :
b110 <
b110 =
1*
#190000
0*
#195000
b11011011 '
b11011011 6
b1000 5
b111011011 4
1$
b1110 :
b111 <
b111 =
1*
#200000
0*
#205000
b0 '
b0 6
b1001 5
b1000000000 4
1$
b1101 :
b1000 <
b1000 =
1*
#210000
0*
#215000
b1011000 '
b1011000 6
b1010 5
b1001011000 4
1$
b1100 :
b1001 <
b1001 =
1*
#220000
0*
#225000
b10111101 '
b10111101 6
b1011 5
b1010111101 4
1$
b1011 :
b1010 <
b1010 =
1*
#230000
0*
#235000
b1001010 '
b1001010 6
b1100 5
b1101001010 4
1$
b1010 :
b1011 <
b1011 =
1*
#240000
0*
#245000
b11110000 '
b11110000 6
b1101 5
b1111110000 4
1$
b1001 :
b1100 <
b1100 =
1*
#250000
0*
#255000
b10000100 '
b10000100 6
b1110 5
b1110000100 4
1$
b1000 :
b1101 <
b1101 =
1*
#260000
0*
#265000
b10110110 '
b10110110 6
b1111 5
b1110110110 4
1$
b111 :
b1110 <
b1110 =
1*
#270000
0*
#275000
b0 '
b0 6
b0 5
b10000000000 4
1$
b110 :
b1111 <
b1111 =
1*
#280000
0*
#285000
b1000000 '
b1000000 6
b1 5
b1000000 4
1$
b101 :
b10000 <
b10000 =
1*
#290000
0*
#295000
b10100100 '
b10100100 6
b10 5
b10100100 4
1$
b100 :
b10001 <
b10001 =
1*
#300000
0*
#305000
b10110000 '
b10110000 6
b11 5
b10110000 4
1$
b11 :
b10010 <
b10010 =
1*
#310000
0*
#315000
b11010000 '
b11010000 6
b100 5
b11010000 4
1$
b10 :
b10011 <
b10011 =
1*
#320000
0*
#325000
b11111111 '
b11111111 6
b101 5
b11111111 4
1$
b1 :
b10100 <
b10100 =
1*
#330000
0*
#335000
b0 '
b0 6
b110 5
b100000000 4
1$
b0 :
b10101 <
b10101 =
1*
#340000
0*
#345000
1-
b0 ;
1"
b10110 =
1*
#350000
0*
#355000
b11 ;
1*
#360000
0*
#365000
b100 ;
1#
1*
#370000
0*
#375000
b10 .
b0 /
b100000000 1
1*
#380000
b101 ;
b111 7
0#
0*
#385000
b1 .
1*
#390000
b110 7
0*
#395000
b1 (
b1 3
1*
#400000
b101 7
1#
0*
#405000
b10 (
b10 3
b10 /
1*
#410000
b100 7
0#
0*
#415000
b11 (
b11 3
1*
#420000
b11 7
0*
#425000
b100 (
b100 3
1*
#430000
b10 7
0*
#435000
b101 (
b101 3
1*
#440000
b1 7
0*
#445000
b110 (
b110 3
1*
#450000
b0 7
0*
#455000
b111 (
b111 3
1*
#460000
b100 ;
b1000 7
b1 9
b11110 8
0*
#465000
b10 .
b0 (
b1000 3
1*
#470000
b101 ;
b111 7
0*
#475000
b1 .
1*
#480000
b110 7
1#
0*
#485000
b1 (
b1001 3
b100000010 /
1*
#490000
b101 7
0#
0*
#495000
b10 (
b1010 3
1*
#500000
b100 7
1#
0*
#505000
b11 (
b1011 3
b10100000010 /
1*
#510000
b11 7
0#
0*
#515000
b100 (
b1100 3
1*
#520000
b10 7
0*
#525000
b101 (
b1101 3
1*
#530000
b1 7
1#
0*
#535000
b110 (
b1110 3
b10010100000010 /
1*
#540000
b0 7
0#
0*
#545000
b111 (
b1111 3
1*
#550000
b100 ;
b1000 7
b10 9
b11101 8
0*
#555000
b10 .
b0 (
b10000 3
1*
#560000
b101 ;
b111 7
0*
#565000
b1 .
1*
#570000
b110 7
1#
0*
#575000
b1 (
b10001 3
b10010010100000010 /
1*
#580000
b101 7
0#
0*
#585000
b10 (
b10010 3
1*
#590000
b100 7
1#
0*
#595000
b11 (
b10011 3
b1010010010100000010 /
1*
#600000
b11 7
0*
#605000
b100 (
b10100 3
b11010010010100000010 /
1*
#610000
b10 7
0#
0*
#615000
b101 (
b10101 3
1*
#620000
b1 7
0*
#625000
b110 (
b10110 3
1*
#630000
b0 7
0*
#635000
b111 (
b10111 3
1*
#640000
b100 ;
b1000 7
b11 9
b11100 8
0*
#645000
b10 .
b0 (
b11000 3
1*
#650000
b101 ;
b111 7
0*
#655000
b1 .
1*
#660000
b110 7
1#
0*
#665000
b1 (
b11001 3
b1000011010010010100000010 /
1*
#670000
b101 7
0*
#675000
b10 (
b11010 3
b11000011010010010100000010 /
1*
#680000
b100 7
0#
0*
#685000
b11 (
b11011 3
1*
#690000
b11 7
1#
0*
#695000
b100 (
b11100 3
b1011000011010010010100000010 /
1*
#700000
b10 7
0#
0*
#705000
b101 (
b11101 3
1*
#710000
b1 7
0*
#715000
b110 (
b11110 3
1*
#720000
b0 7
0*
#725000
b111 (
b11111 3
1*
#730000
b100 ;
b1000 7
b100 9
b11011 8
0*
#735000
b10 .
b0 (
b100000 3
1*
#740000
b101 ;
b111 7
0*
#745000
b1 .
1*
#750000
b110 7
1#
0*
#755000
b1 (
b100001 3
b100001011000011010010010100000010 /
1*
#760000
b101 7
0*
#765000
b10 (
b100010 3
b1100001011000011010010010100000010 /
1*
#770000
b100 7
0*
#775000
b11 (
b100011 3
b11100001011000011010010010100000010 /
1*
#780000
b11 7
0*
#785000
b100 (
b100100 3
b111100001011000011010010010100000010 /
1*
#790000
b10 7
0*
#795000
b101 (
b100101 3
b1111100001011000011010010010100000010 /
1*
#800000
b1 7
0*
#805000
b110 (
b100110 3
b11111100001011000011010010010100000010 /
1*
#810000
b0 7
0*
#815000
b111 (
b100111 3
b111111100001011000011010010010100000010 /
1*
#820000
b100 ;
b1000 7
b101 9
b11010 8
0*
#825000
b10 .
b0 (
b101000 3
b1111111100001011000011010010010100000010 /
1*
#830000
b101 ;
b111 7
0#
0*
#835000
b1 .
1*
#840000
b110 7
0*
#845000
b1 (
b101001 3
1*
#850000
b101 7
0*
#855000
b10 (
b101010 3
1*
#860000
b100 7
0*
#865000
b11 (
b101011 3
1*
#870000
b11 7
0*
#875000
b100 (
b101100 3
1*
#880000
b10 7
0*
#885000
b101 (
b101101 3
1*
#890000
b1 7
0*
#895000
b110 (
b101110 3
1*
#900000
b0 7
0*
#905000
b111 (
b101111 3
1*
#910000
b100 ;
b1000 7
b110 9
b11001 8
0*
#915000
b10 .
b0 (
b110000 3
1*
#920000
b101 ;
b111 7
0*
#925000
b1 .
1*
#930000
b110 7
0*
#935000
b1 (
b110001 3
1*
#940000
b101 7
1#
0*
#945000
b10 (
b110010 3
b10000000001111111100001011000011010010010100000010 /
1*
#950000
b100 7
0#
0*
#955000
b11 (
b110011 3
1*
#960000
b11 7
1#
0*
#965000
b100 (
b110100 3
b1010000000001111111100001011000011010010010100000010 /
1*
#970000
b10 7
0*
#975000
b101 (
b110101 3
b11010000000001111111100001011000011010010010100000010 /
1*
#980000
b1 7
0*
#985000
b110 (
b110110 3
b111010000000001111111100001011000011010010010100000010 /
1*
#990000
b0 7
0*
#995000
b111 (
b110111 3
b1111010000000001111111100001011000011010010010100000010 /
1*
#1000000
b100 ;
b1000 7
b111 9
b11000 8
0#
0*
#1005000
b10 .
b0 (
b111000 3
1*
#1010000
b101 ;
b111 7
0*
#1015000
b1 .
1*
#1020000
b110 7
1#
0*
#1025000
b1 (
b111001 3
b101111010000000001111111100001011000011010010010100000010 /
1*
#1030000
b101 7
0*
#1035000
b10 (
b111010 3
b1101111010000000001111111100001011000011010010010100000010 /
1*
#1040000
b100 7
0#
0*
#1045000
b11 (
b111011 3
1*
#1050000
b11 7
1#
0*
#1055000
b100 (
b111100 3
b101101111010000000001111111100001011000011010010010100000010 /
1*
#1060000
b10 7
0*
#1065000
b101 (
b111101 3
b1101101111010000000001111111100001011000011010010010100000010 /
1*
#1070000
b1 7
0#
0*
#1075000
b110 (
b111110 3
1*
#1080000
b0 7
1#
0*
#1085000
b111 (
b111111 3
b101101101111010000000001111111100001011000011010010010100000010 /
1*
#1090000
b100 ;
b1000 7
b1000 9
b10111 8
0*
#1095000
b10 .
b0 (
b1000000 3
b1101101101111010000000001111111100001011000011010010010100000010 /
1*
#1100000
b101 ;
b111 7
0#
0*
#1105000
b1 .
1*
#1110000
b110 7
0*
#1115000
b1 (
b1000001 3
1*
#1120000
b101 7
0*
#1125000
b10 (
b1000010 3
1*
#1130000
b100 7
0*
#1135000
b11 (
b1000011 3
1*
#1140000
b11 7
0*
#1145000
b100 (
b1000100 3
1*
#1150000
b10 7
0*
#1155000
b101 (
b1000101 3
1*
#1160000
b1 7
0*
#1165000
b110 (
b1000110 3
1*
#1170000
b0 7
0*
#1175000
b111 (
b1000111 3
1*
#1180000
b100 ;
b1000 7
b1001 9
b10110 8
0*
#1185000
b10 .
b0 (
b1001000 3
1*
#1190000
b101 ;
b111 7
0*
#1195000
b1 .
1*
#1200000
b110 7
0*
#1205000
b1 (
b1001001 3
1*
#1210000
b101 7
1#
0*
#1215000
b10 (
b1001010 3
b10000000001101101101111010000000001111111100001011000011010010010100000010 /
1*
#1220000
b100 7
0#
0*
#1225000
b11 (
b1001011 3
1*
#1230000
b11 7
1#
0*
#1235000
b100 (
b1001100 3
b1010000000001101101101111010000000001111111100001011000011010010010100000010 /
1*
#1240000
b10 7
0*
#1245000
b101 (
b1001101 3
b11010000000001101101101111010000000001111111100001011000011010010010100000010 /
1*
#1250000
b1 7
0#
0*
#1255000
b110 (
b1001110 3
1*
#1260000
b0 7
0*
#1265000
b111 (
b1001111 3
1*
#1270000
b100 ;
b1000 7
b1010 9
b10101 8
0*
#1275000
b10 .
b0 (
b1010000 3
1*
#1280000
b101 ;
b111 7
0*
#1285000
b1 .
1*
#1290000
b110 7
1#
0*
#1295000
b1 (
b1010001 3
b100011010000000001101101101111010000000001111111100001011000011010010010100000010 /
1*
#1300000
b101 7
0#
0*
#1305000
b10 (
b1010010 3
1*
#1310000
b100 7
1#
0*
#1315000
b11 (
b1010011 3
b10100011010000000001101101101111010000000001111111100001011000011010010010100000010 /
1*
#1320000
b11 7
0*
#1325000
b100 (
b1010100 3
b110100011010000000001101101101111010000000001111111100001011000011010010010100000010 /
1*
#1330000
b10 7
0*
#1335000
b101 (
b1010101 3
b1110100011010000000001101101101111010000000001111111100001011000011010010010100000010 /
1*
#1340000
b1 7
0*
#1345000
b110 (
b1010110 3
b11110100011010000000001101101101111010000000001111111100001011000011010010010100000010 /
1*
#1350000
b0 7
0#
0*
#1355000
b111 (
b1010111 3
1*
#1360000
b100 ;
b1000 7
b1011 9
b10100 8
1#
0*
#1365000
b10 .
b0 (
b1011000 3
b1011110100011010000000001101101101111010000000001111111100001011000011010010010100000010 /
1*
#1370000
b101 ;
b111 7
0#
0*
#1375000
b1 .
1*
#1380000
b110 7
0*
#1385000
b1 (
b1011001 3
1*
#1390000
b101 7
1#
0*
#1395000
b10 (
b1011010 3
b101011110100011010000000001101101101111010000000001111111100001011000011010010010100000010 /
1*
#1400000
b100 7
0#
0*
#1405000
b11 (
b1011011 3
1*
#1410000
b11 7
0*
#1415000
b100 (
b1011100 3
1*
#1420000
b10 7
1#
0*
#1425000
b101 (
b1011101 3
b100101011110100011010000000001101101101111010000000001111111100001011000011010010010100000010 /
1*
#1430000
b1 7
0#
0*
#1435000
b110 (
b1011110 3
1*
#1440000
b0 7
1#
0*
#1445000
b111 (
b1011111 3
b10100101011110100011010000000001101101101111010000000001111111100001011000011010010010100000010 /
1*
#1450000
b100 ;
b1000 7
b1100 9
b10011 8
0#
0*
#1455000
b10 .
b0 (
b1100000 3
1*
#1460000
b101 ;
b111 7
0*
#1465000
b1 .
1*
#1470000
b110 7
1#
0*
#1475000
b1 (
b1100001 3
b1010100101011110100011010000000001101101101111010000000001111111100001011000011010010010100000010 /
1*
#1480000
b101 7
0*
#1485000
b10 (
b1100010 3
b11010100101011110100011010000000001101101101111010000000001111111100001011000011010010010100000010 /
1*
#1490000
b100 7
0*
#1495000
b11 (
b1100011 3
b111010100101011110100011010000000001101101101111010000000001111111100001011000011010010010100000010 /
1*
#1500000
b11 7
0*
#1505000
b100 (
b1100100 3
b1111010100101011110100011010000000001101101101111010000000001111111100001011000011010010010100000010 /
1*
#1510000
b10 7
0#
0*
#1515000
b101 (
b1100101 3
1*
#1520000
b1 7
0*
#1525000
b110 (
b1100110 3
1*
#1530000
b0 7
0*
#1535000
b111 (
b1100111 3
1*
#1540000
b100 ;
b1000 7
b1101 9
b10010 8
0*
#1545000
b10 .
b0 (
b1101000 3
1*
#1550000
b101 ;
b111 7
0*
#1555000
b1 .
1*
#1560000
b110 7
1#
0*
#1565000
b1 (
b1101001 3
b100001111010100101011110100011010000000001101101101111010000000001111111100001011000011010010010100000010 /
1*
#1570000
b101 7
0#
0*
#1575000
b10 (
b1101010 3
1*
#1580000
b100 7
0*
#1585000
b11 (
b1101011 3
1*
#1590000
b11 7
0*
#1595000
b100 (
b1101100 3
1*
#1600000
b10 7
0*
#1605000
b101 (
b1101101 3
1*
#1610000
b1 7
1#
0*
#1615000
b110 (
b1101110 3
b10000100001111010100101011110100011010000000001101101101111010000000001111111100001011000011010010010100000010 /
1*
#1620000
b0 7
0#
0*
#1625000
b111 (
b1101111 3
1*
#1630000
b100 ;
b1000 7
b1110 9
b10001 8
0*
#1635000
b10 .
b0 (
b1110000 3
1*
#1640000
b101 ;
b111 7
0*
#1645000
b1 .
1*
#1650000
b110 7
1#
0*
#1655000
b1 (
b1110001 3
b10010000100001111010100101011110100011010000000001101101101111010000000001111111100001011000011010010010100000010 /
1*
#1660000
b101 7
0#
0*
#1665000
b10 (
b1110010 3
1*
#1670000
b100 7
1#
0*
#1675000
b11 (
b1110011 3
b1010010000100001111010100101011110100011010000000001101101101111010000000001111111100001011000011010010010100000010 /
1*
#1680000
b11 7
0*
#1685000
b100 (
b1110100 3
b11010010000100001111010100101011110100011010000000001101101101111010000000001111111100001011000011010010010100000010 /
1*
#1690000
b10 7
0#
0*
#1695000
b101 (
b1110101 3
1*
#1700000
b1 7
1#
0*
#1705000
b110 (
b1110110 3
b1011010010000100001111010100101011110100011010000000001101101101111010000000001111111100001011000011010010010100000010 /
1*
#1710000
b0 7
0*
#1715000
b111 (
b1110111 3
b11011010010000100001111010100101011110100011010000000001101101101111010000000001111111100001011000011010010010100000010 /
1*
#1720000
b100 ;
b1000 7
b1111 9
b10000 8
0#
0*
#1725000
b10 .
b0 (
b1111000 3
1*
#1730000
b101 ;
b111 7
0*
#1735000
b1 .
1*
#1740000
b110 7
0*
#1745000
b1 (
b1111001 3
1*
#1750000
b101 7
0*
#1755000
b10 (
b1111010 3
1*
#1760000
b100 7
0*
#1765000
b11 (
b1111011 3
1*
#1770000
b11 7
0*
#1775000
b100 (
b1111100 3
1*
#1780000
b10 7
0*
#1785000
b101 (
b1111101 3
1*
#1790000
b1 7
0*
#1795000
b110 (
b1111110 3
1*
#1800000
b0 7
0*
#1805000
b111 (
b1111111 3
1*
#1810000
b100 ;
b1000 7
b10000 9
b1111 8
0*
#1815000
b10 .
b0 (
b10000000 3
1*
#1820000
b101 ;
b111 7
0*
#1825000
b1 .
1*
#1830000
b110 7
0*
#1835000
b1 (
b10000001 3
1*
#1840000
b101 7
1#
0*
#1845000
b10 (
b10000010 3
b1000000000011011010010000100001111010100101011110100011010000000001101101101111010000000001111111100001011000011010010010100000010 /
1*
#1850000
b100 7
0#
0*
#1855000
b11 (
b10000011 3
1*
#1860000
b11 7
0*
#1865000
b100 (
b10000100 3
1*
#1870000
b10 7
0*
#1875000
b101 (
b10000101 3
1*
#1880000
b1 7
0*
#1885000
b110 (
b10000110 3
1*
#1890000
b0 7
0*
#1895000
b111 (
b10000111 3
1*
#1900000
b100 ;
b1000 7
b10001 9
b1110 8
0*
#1905000
b10 .
b0 (
b10001000 3
1*
#1910000
b101 ;
b111 7
0*
#1915000
b1 .
1*
#1920000
b110 7
1#
0*
#1925000
b1 (
b10001001 3
b10000001000000000011011010010000100001111010100101011110100011010000000001101101101111010000000001111111100001011000011010010010100000010 /
1*
#1930000
b101 7
0#
0*
#1935000
b10 (
b10001010 3
1*
#1940000
b100 7
1#
0*
#1945000
b11 (
b10001011 3
b1010000001000000000011011010010000100001111010100101011110100011010000000001101101101111010000000001111111100001011000011010010010100000010 /
1*
#1950000
b11 7
0#
0*
#1955000
b100 (
b10001100 3
1*
#1960000
b10 7
0*
#1965000
b101 (
b10001101 3
1*
#1970000
b1 7
1#
0*
#1975000
b110 (
b10001110 3
b1001010000001000000000011011010010000100001111010100101011110100011010000000001101101101111010000000001111111100001011000011010010010100000010 /
1*
#1980000
b0 7
0#
0*
#1985000
b111 (
b10001111 3
1*
#1990000
b100 ;
b1000 7
b10010 9
b1101 8
0*
#1995000
b10 .
b0 (
b10010000 3
1*
#2000000
b101 ;
b111 7
0*
#2005000
b1 .
1*
#2010000
b110 7
1#
0*
#2015000
b1 (
b10010001 3
b1001001010000001000000000011011010010000100001111010100101011110100011010000000001101101101111010000000001111111100001011000011010010010100000010 /
1*
#2020000
b101 7
0#
0*
#2025000
b10 (
b10010010 3
1*
#2030000
b100 7
1#
0*
#2035000
b11 (
b10010011 3
b101001001010000001000000000011011010010000100001111010100101011110100011010000000001101101101111010000000001111111100001011000011010010010100000010 /
1*
#2040000
b11 7
0*
#2045000
b100 (
b10010100 3
b1101001001010000001000000000011011010010000100001111010100101011110100011010000000001101101101111010000000001111111100001011000011010010010100000010 /
1*
#2050000
b10 7
0#
0*
#2055000
b101 (
b10010101 3
1*
#2060000
b1 7
0*
#2065000
b110 (
b10010110 3
1*
#2070000
b0 7
0*
#2075000
b111 (
b10010111 3
1*
#2080000
b100 ;
b1000 7
b10011 9
b1100 8
0*
#2085000
b10 .
b0 (
b10011000 3
1*
#2090000
b101 ;
b111 7
0*
#2095000
b1 .
1*
#2100000
b110 7
1#
0*
